AxPdfSigner/__init__.py
AxPdfSigner/_core.py
AxPdfSigner/_license.py
AxPdfSigner/signer.py
AxPdfSigner/_lib/axBridge_python.dll
AxPdfSigner/_lib/itextsharp.dll
AxPdfSigner/_lib/itextsharp.licensekey.dll
axpdfsigner-1.0.4.dist-info/licenses/LICENSE
axpdfsigner-1.0.4.dist-info/METADATA
axpdfsigner-1.0.4.dist-info/WHEEL
axpdfsigner-1.0.4.dist-info/top_level.txt
axpdfsigner-1.0.4.dist-info/RECORD
