Metadata-Version: 2.4
Name: AxPdfSigner
Version: 1.0.4
Summary: Professional PDF Digital Signature SDK - Pure Python Implementation
Home-page: https://axonatetech.com/
Author: Axonate Tech
Author-email: Axonate Tech <support@axonatetech.com>
License: Commercial
Project-URL: Homepage, https://axonatetech.com/
Project-URL: Documentation, https://axonatetech.com/docs
Project-URL: Support, https://axonatetech.com/support
Keywords: pdf,signature,digital-signature,signing,certificate,pfx,python
Classifier: Development Status :: 5 - Production/Stable
Classifier: Intended Audience :: Developers
Classifier: Topic :: Software Development :: Libraries :: Python Modules
Classifier: Topic :: Office/Business
Classifier: Topic :: Security :: Cryptography
Classifier: License :: Other/Proprietary License
Classifier: Programming Language :: Python :: 3
Classifier: Programming Language :: Python :: 3.7
Classifier: Programming Language :: Python :: 3.8
Classifier: Programming Language :: Python :: 3.9
Classifier: Programming Language :: Python :: 3.10
Classifier: Programming Language :: Python :: 3.11
Classifier: Programming Language :: Python :: 3.12
Classifier: Operating System :: Microsoft :: Windows
Requires-Python: >=3.7
License-File: LICENSE
Requires-Dist: pythonnet>=3.0.0
Dynamic: author
Dynamic: home-page
Dynamic: license-file
Dynamic: requires-python
